niklibpy/__init__.py
niklibpy/niklib.py
niklibpy-0.1.3.dist-info/METADATA
niklibpy-0.1.3.dist-info/WHEEL
niklibpy-0.1.3.dist-info/RECORD
