Metadata-Version: 2.1
Name: niklibpy
Version: 0.1.3
Summary: 
Author: Nik V
Author-email: github@nikvdp.com
Requires-Python: >=3.9,<4.0
Classifier: Programming Language :: Python :: 3
Classifier: Programming Language :: Python :: 3.9
Classifier: Programming Language :: Python :: 3.10
Classifier: Programming Language :: Python :: 3.11
Classifier: Programming Language :: Python :: 3.12
